pros/__init__.py
pros/autocomplete/pros-complete.bash
pros/autocomplete/pros-complete.ps1
pros/autocomplete/pros-complete.zsh
pros/autocomplete/pros.fish
pros/cli/__init__.py
pros/cli/build.py
pros/cli/click_classes.py
pros/cli/common.py
pros/cli/conductor.py
pros/cli/conductor_utils.py
pros/cli/interactive.py
pros/cli/main.py
pros/cli/misc_commands.py
pros/cli/terminal.py
pros/cli/test.py
pros/cli/upload.py
pros/cli/user_script.py
pros/cli/v5_utils.py
pros/common/__init__.py
pros/common/sentry.py
pros/common/utils.py
pros/common/ui/__init__.py
pros/common/ui/log.py
pros/common/ui/interactive/ConfirmModal.py
pros/common/ui/interactive/__init__.py
pros/common/ui/interactive/application.py
pros/common/ui/interactive/observable.py
pros/common/ui/interactive/components/__init__.py
pros/common/ui/interactive/components/button.py
pros/common/ui/interactive/components/checkbox.py
pros/common/ui/interactive/components/component.py
pros/common/ui/interactive/components/container.py
pros/common/ui/interactive/components/input.py
pros/common/ui/interactive/components/input_groups.py
pros/common/ui/interactive/components/label.py
pros/common/ui/interactive/parameters/__init__.py
pros/common/ui/interactive/parameters/misc_parameters.py
pros/common/ui/interactive/parameters/parameter.py
pros/common/ui/interactive/parameters/validatable_parameter.py
pros/common/ui/interactive/renderers/MachineOutputRenderer.py
pros/common/ui/interactive/renderers/Renderer.py
pros/common/ui/interactive/renderers/__init__.py
pros/conductor/__init__.py
pros/conductor/conductor.py
pros/conductor/transaction.py
pros/conductor/depots/__init__.py
pros/conductor/depots/depot.py
pros/conductor/depots/http_depot.py
pros/conductor/depots/local_depot.py
pros/conductor/interactive/NewProjectModal.py
pros/conductor/interactive/UpdateProjectModal.py
pros/conductor/interactive/__init__.py
pros/conductor/interactive/components.py
pros/conductor/interactive/parameters.py
pros/conductor/project/ProjectReport.py
pros_cli-3.5.6.dist-info/LICENSE
pros_cli-3.5.6.dist-info/METADATA
pros_cli-3.5.6.dist-info/WHEEL
pros_cli-3.5.6.dist-info/entry_points.txt
pros_cli-3.5.6.dist-info/top_level.txt
pros_cli-3.5.6.dist-info/RECORD
